typica/__init__.py
typica/base.py
typica/connection.py
typica/metadata.py
typica/modules/cclickhouse.py
typica/modules/ckafka.py
typica/modules/pmongo.py
typica/modules/psycopg.py
typica/modules/psycopg_alchemy.py
typica/modules/redis.py
typica/response.py
typica/schema.py
typica/utils/__init__.py
typica/utils/config.py
typica/utils/enums.py
typica/utils/log.py
module_typica-0.2.11.dist-info/METADATA
module_typica-0.2.11.dist-info/WHEEL
module_typica-0.2.11.dist-info/RECORD
