Metadata-Version: 2.3
Name: module-typica
Version: 0.2.11
Summary: Standard Pydantic usages & utilities
Author: Oktapian
Author-email: oktapian1998@gmail.com
Requires-Python: >=3.10,<4.0
Classifier: Programming Language :: Python :: 3
Classifier: Programming Language :: Python :: 3.10
Classifier: Programming Language :: Python :: 3.11
Classifier: Programming Language :: Python :: 3.12
Classifier: Programming Language :: Python :: 3.13
Requires-Dist: deprecated (>=1.2.14,<2.0.0)
Requires-Dist: pydantic (>=2.9.2,<3.0.0)
Requires-Dist: pydantic-settings (>=2.6.1,<3.0.0)
Requires-Dist: pytz (>=2025.2,<2026.0)
